<!-- Indices written at Mon, 4 Feb 2013 19:54:50 PST -->

<datastore-indexes>

    <!-- Used 4 times in query history -->
    <datastore-index kind="Activity" ancestor="false" source="auto">
        <property name="activityType" direction="asc"/>
        <property name="userEmail" direction="asc"/>
        <property name="time" direction="asc"/>
    </datastore-index>

    <!-- Used 1 time in query history -->
    <datastore-index kind="Activity" ancestor="false" source="auto">
        <property name="activityType" direction="asc"/>
        <property name="itemId" direction="asc"/>
        <property name="time" direction="desc"/>
    </datastore-index>

    <!-- Used 1 time in query history -->
    <datastore-index kind="Activity" ancestor="false" source="auto">
        <property name="itemId" direction="asc"/>
        <property name="time" direction="desc"/>
    </datastore-index>

</datastore-indexes>
